crawling9/crawling.py
crawling9-0.0.1.dist-info/LICENSE
crawling9-0.0.1.dist-info/METADATA
crawling9-0.0.1.dist-info/WHEEL
crawling9-0.0.1.dist-info/top_level.txt
crawling9-0.0.1.dist-info/RECORD
