Metadata-Version: 2.1
Name: crawling9
Version: 0.0.1
Summary: oss-dev my crawling 0001
Home-page: https://github.com/ParkSeungMin1/crawling.git
Download-URL: https://github.com/ParkSeungMin1/crawling.git/archive/refs/tags/v0.0.1.zip
Author: seungminpark
Author-email: 1828421@donga.ac.kr
License: UNKNOWN
Platform: UNKNOWN
Classifier: Programming Language :: Python :: 3
Classifier: Operating System :: OS Independent
License-File: LICENSE
Requires-Dist: pytest
